rich_logger/__init__.py
rich_logger/__main__.py
rich_logger/py.typed
rich_logger/sink.py
rich_logger/logs/run.txt
rich_logger/logs/trace.log
rich_loguru_sink-0.0.1.dist-info/METADATA
rich_loguru_sink-0.0.1.dist-info/WHEEL
rich_loguru_sink-0.0.1.dist-info/entry_points.txt
rich_loguru_sink-0.0.1.dist-info/RECORD
